setup.py
distrib_probabilidad/Binomialdistribution.py
distrib_probabilidad/Gaussiandistribution.py
distrib_probabilidad/Generaldistribution.py
distrib_probabilidad/__init__.py
distrib_probabilidad.egg-info/PKG-INFO
distrib_probabilidad.egg-info/SOURCES.txt
distrib_probabilidad.egg-info/dependency_links.txt
distrib_probabilidad.egg-info/not-zip-safe
distrib_probabilidad.egg-info/top_level.txt