Metadata-Version: 1.0
Name: distrib-probabilidad
Version: 1.0
Summary: Gaussian and Binomial distributions
Home-page: UNKNOWN
Author: Hairo Ulises Miranda Belmonte
Author-email: hairo1421@gmail.com
License: UNKNOWN
Platform: UNKNOWN
